pygifconvt_hyeonu/__init__.py
pygifconvt_hyeonu/converter_hyeonu.py
pygifconvt_hyeonu-1.0.1.dist-info/LICENSE
pygifconvt_hyeonu-1.0.1.dist-info/METADATA
pygifconvt_hyeonu-1.0.1.dist-info/WHEEL
pygifconvt_hyeonu-1.0.1.dist-info/top_level.txt
pygifconvt_hyeonu-1.0.1.dist-info/RECORD
